Workbook

Sheet Resumen
A1: Mangueras PVC · Xiandai (2026) vs Dongying Wanhe (2021)
A2: Tamarama SpA · análisis del 16-sep-2026 · precios FOB China en US$
A4: Proveedor nuevo | B4: Weifang Xiandai Plastics & Rubbers · cotización XDQ260916 del 16-sep-2026
A5: Proveedor anterior | B5: Dongying Wanhe Rubber & Plastic · último precio: proforma DYWH20210607CH01 del 7-jun-2021
A6: Motivo del cambio | B6: El proveedor anterior tiene problemas de durabilidad en terreno (reclamo de clientes)
A8: SUCCIÓN (amarilla) | B8: Precio por metro parecido: de −14% (3") a +34% (1-1/4"). Xiandai tiene paredes más gruesas y es 9% más barato por kilo (US$ 1,95 vs 2,15/kg).
A9: JARDÍN (verde) | B9: Xiandai es 51% a 95% más caro por metro (US$ 2,26 vs 1,51/kg). Hay que negociar o buscar otro fabricante.
A10: Pedido tipo 2021 | B10: Mismos metros: Dongying US$ 21.016 vs Xiandai US$ 26.239 (+25%). Volumen: 71 m³ vs 93 m³ (no cabe en un 40HQ).
A12: ⚠ Falta en la cotización | B12: Presión de trabajo y de rotura, vacío, radio de curvatura, temperatura, protección UV, ficha técnica (lo pediste el 14-sep).
A13: ⚠ Informe SGS | B13: Es de otra manguera (reforzada con fibra roja/blanca/negra). Solo RoHS (no mide durabilidad). Dice «solo referencia interna».
A15: RECOMENDACIÓN | B15: 1) Pedir ficha técnica completa y muestras (succión 1" y jardín 3/4") para probar en terreno.
B16: 2) Pedir material por escrito: PVC virgen, % de carga (carbonato), plastificante (DOTP mejor que DOP), aditivo UV.
B17: 3) Pedir plan de carga del 40HQ y precio con embalaje (su precio no incluye cajas ni pallets).
B18: 4) Exigir Certificado de Origen Form F (arancel 0% con TLC Chile-China; sin él, 6%).
B19: 5) Negociar precio de jardín. Succión: Xiandai es la mejor apuesta, sujeta a muestras.
B20: 6) No cerrar sin ficha técnica, prueba de muestras y Form F.

Sheet Comparación
A1: Comparación por medida
A2: Datos de las cotizaciones; columnas en gris se calculan con fórmulas
A4: Tipo | B4: Medida | C4: DW largo rollo (m) | D4: DW kg/rollo | E4: DW m³/rollo | F4: DW US$/rollo | G4: DW DI mm | H4: DW DE mm | I4: DW pared mm | J4: DW P. trabajo bar | K4: DW P. rotura bar | L4: XD largo rollo (m) | M4: XD kg/rollo | N4: XD m³/rollo | O4: XD US$/rollo | P4: XD DI mm | Q4: XD DE mm | R4: XD MOQ (m) | S4: DW US$/m | T4: XD US$/m | U4: Dif. US$/m | V4: DW kg/m | W4: XD kg/m | X4: DW US$/kg | Y4: XD US$/kg | Z4: XD pared mm
A5: Succión | B5: 1" | C5: 50 | D5: 16.5 | E5: 0.072 | F5: 35.5 | G5: 25 | H5: 30 | I5: 2.5 | J5: 8 | K5: 24 | L5: 30 | M5: 12.78 | N5: 0.1 | O5: 24.98 | P5: 25 | Q5: 32 | R5: 1000 | S5: =F5/C5 -> 0.71 | T5: =O5/L5 -> 0.83266667 | U5: =T5/S5-1 -> 0.17276995 | V5: =D5/C5 -> 0.33 | W5: =M5/L5 -> 0.426 | X5: =F5/D5 -> 2.1515152 | Y5: =O5/M5 -> 1.9546166 | Z5: =(Q5-P5)/2 -> 3.5
A6: Succión | B6: 1-1/4" | C6: 50 | D6: 21 | E6: 0.185 | F6: 45 | G6: 32 | H6: 38 | I6: 3 | J6: 8 | K6: 24 | L6: 30 | M6: 18.45 | N6: 0.15 | O6: 36.06 | P6: 32 | Q6: 40 | R6: 1000 | S6: =F6/C6 -> 0.9 | T6: =O6/L6 -> 1.202 | U6: =T6/S6-1 -> 0.33555556 | V6: =D6/C6 -> 0.42 | W6: =M6/L6 -> 0.615 | X6: =F6/D6 -> 2.1428571 | Y6: =O6/M6 -> 1.9544715 | Z6: =(Q6-P6)/2 -> 4
A7: Succión | B7: 1-1/2" | C7: 50 | D7: 31.5 | E7: 0.195 | F7: 67.5 | G7: 38 | H7: 45 | I7: 3.5 | J7: 8 | K7: 24 | L7: 30 | M7: 21.52 | N7: 0.2 | O7: 42.07 | P7: 38 | Q7: 46 | R7: 1000 | S7: =F7/C7 -> 1.35 | T7: =O7/L7 -> 1.4023333 | U7: =T7/S7-1 -> 0.038765432 | V7: =D7/C7 -> 0.63 | W7: =M7/L7 -> 0.71733333 | X7: =F7/D7 -> 2.1428571 | Y7: =O7/M7 -> 1.9549257 | Z7: =(Q7-P7)/2 -> 4
A8: Succión | B8: 2" | C8: 50 | D8: 47.5 | E8: 0.22 | F8: 102 | G8: 50 | H8: 58 | I8: 4 | J8: 7 | K8: 21 | L8: 30 | M8: 32 | N8: 0.3 | O8: 62.55 | P8: 51 | Q8: 60 | R8: 1000 | S8: =F8/C8 -> 2.04 | T8: =O8/L8 -> 2.085 | U8: =T8/S8-1 -> 0.022058824 | V8: =D8/C8 -> 0.95 | W8: =M8/L8 -> 1.0666667 | X8: =F8/D8 -> 2.1473684 | Y8: =O8/M8 -> 1.9546875 | Z8: =(Q8-P8)/2 -> 4.5
A9: Succión | B9: 3" | C9: 25 | D9: 45.5 | E9: 0.432 | F9: 98 | G9: 75 | H9: 85 | I9: 5 | J9: 5 | K9: 15 | L9: 30 | M9: 51.89 | N9: 0.46 | O9: 101.43 | P9: 76 | Q9: 86 | R9: 600 | S9: =F9/C9 -> 3.92 | T9: =O9/L9 -> 3.381 | U9: =T9/S9-1 -> -0.1375 | V9: =D9/C9 -> 1.82 | W9: =M9/L9 -> 1.7296667 | X9: =F9/D9 -> 2.1538462 | Y9: =O9/M9 -> 1.9547119 | Z9: =(Q9-P9)/2 -> 5
A10: Succión | B10: 4" | C10: 25 | D10: 78.75 | E10: 1.6 | F10: 169 | G10: 100 | H10: 112 | I10: 6 | J10: 5 | K10: 15 | L10: 30 | M10: 97.75 | N10: 1.04 | O10: 191.09 | P10: 102 | Q10: 116 | R10: 600 | S10: =F10/C10 -> 6.76 | T10: =O10/L10 -> 6.3696667 | U10: =T10/S10-1 -> -0.057741617 | V10: =D10/C10 -> 3.15 | W10: =M10/L10 -> 3.2583333 | X10: =F10/D10 -> 2.1460317 | Y10: =O10/M10 -> 1.9548849 | Z10: =(Q10-P10)/2 -> 7
A11: Jardín | B11: 1/2" | C11: 100 | D11: 12 | E11: 0.038 | F11: 18 | G11: 12 | H11: 16 | I11: 2 | J11: 8 | K11: 15 | L11: 50 | M11: 7.8 | N11: 0.058 | O11: 17.59 | P11: 12 | Q11: 17 | R11: 3000 | S11: =F11/C11 -> 0.18 | T11: =O11/L11 -> 0.3518 | U11: =T11/S11-1 -> 0.95444444 | V11: =D11/C11 -> 0.12 | W11: =M11/L11 -> 0.156 | X11: =F11/D11 -> 1.5 | Y11: =O11/M11 -> 2.2551282 | Z11: =(Q11-P11)/2 -> 2.5
A12: Jardín | B12: 3/4" | C12: 100 | D12: 22.8 | E12: 0.05 | F12: 34.5 | G12: 19 | H12: 24 | I12: 2.5 | J12: 5 | K12: 15 | L12: 50 | M12: 11.56 | N12: 0.068 | O12: 26.08 | P12: 19 | Q12: 24 | R12: 2000 | S12: =F12/C12 -> 0.345 | T12: =O12/L12 -> 0.5216 | U12: =T12/S12-1 -> 0.51188406 | V12: =D12/C12 -> 0.228 | W12: =M12/L12 -> 0.2312 | X12: =F12/D12 -> 1.5131579 | Y12: =O12/M12 -> 2.2560554 | Z12: =(Q12-P12)/2 -> 2.5
A13: Jardín | B13: 1" | C13: 50 | D13: 17.8 | E13: 0.072 | F13: 27 | G13: 25 | H13: 31 | I13: 3 | J13: 4 | K13: 12 | L13: 50 | M13: 18.07 | N13: 0.096 | O13: 40.75 | P13: 25 | Q13: 31 | R13: 2000 | S13: =F13/C13 -> 0.54 | T13: =O13/L13 -> 0.815 | U13: =T13/S13-1 -> 0.50925926 | V13: =D13/C13 -> 0.356 | W13: =M13/L13 -> 0.3614 | X13: =F13/D13 -> 1.5168539 | Y13: =O13/M13 -> 2.255119 | Z13: =(Q13-P13)/2 -> 3
A15: DW = Dongying Wanhe (7-jun-2021) · XD = Xiandai (16-sep-2026) · Xiandai no informó presiones (pendiente).

Sheet Pedido tipo
A1: Mismo pedido de 2021 con los precios de cada proveedor
A2: Metros de la proforma de junio-2021 (1 contenedor 40HQ)
A4: Tipo | B4: Medida | C4: Metros | D4: DW US$ | E4: XD US$ | F4: Diferencia US$ | G4: DW m³ | H4: XD m³
A5: Succión | B5: 1" | C5: 300 | D5: =C5*'Comparación'!S5 -> 213 | E5: =C5*'Comparación'!T5 -> 249.8 | F5: =E5-D5 -> 36.8 | G5: =C5*'Comparación'!E5/'Comparación'!C5 -> 0.432 | H5: =C5*'Comparación'!N5/'Comparación'!L5 -> 1
A6: Succión | B6: 1-1/4" | C6: 200 | D6: =C6*'Comparación'!S6 -> 180 | E6: =C6*'Comparación'!T6 -> 240.4 | F6: =E6-D6 -> 60.4 | G6: =C6*'Comparación'!E6/'Comparación'!C6 -> 0.74 | H6: =C6*'Comparación'!N6/'Comparación'!L6 -> 1
A7: Succión | B7: 1-1/2" | C7: 600 | D7: =C7*'Comparación'!S7 -> 810 | E7: =C7*'Comparación'!T7 -> 841.4 | F7: =E7-D7 -> 31.4 | G7: =C7*'Comparación'!E7/'Comparación'!C7 -> 2.34 | H7: =C7*'Comparación'!N7/'Comparación'!L7 -> 4
A8: Succión | B8: 2" | C8: 1500 | D8: =C8*'Comparación'!S8 -> 3060 | E8: =C8*'Comparación'!T8 -> 3127.5 | F8: =E8-D8 -> 67.5 | G8: =C8*'Comparación'!E8/'Comparación'!C8 -> 6.6 | H8: =C8*'Comparación'!N8/'Comparación'!L8 -> 15
A9: Succión | B9: 3" | C9: 1000 | D9: =C9*'Comparación'!S9 -> 3920 | E9: =C9*'Comparación'!T9 -> 3381 | F9: =E9-D9 -> -539 | G9: =C9*'Comparación'!E9/'Comparación'!C9 -> 17.28 | H9: =C9*'Comparación'!N9/'Comparación'!L9 -> 15.333333
A10: Succión | B10: 4" | C10: 425 | D10: =C10*'Comparación'!S10 -> 2873 | E10: =C10*'Comparación'!T10 -> 2707.1083 | F10: =E10-D10 -> -165.89167 | G10: =C10*'Comparación'!E10/'Comparación'!C10 -> 27.2 | H10: =C10*'Comparación'!N10/'Comparación'!L10 -> 14.733333
A11: Jardín | B11: 1/2" | C11: 8000 | D11: =C11*'Comparación'!S11 -> 1440 | E11: =C11*'Comparación'!T11 -> 2814.4 | F11: =E11-D11 -> 1374.4 | G11: =C11*'Comparación'!E11/'Comparación'!C11 -> 3.04 | H11: =C11*'Comparación'!N11/'Comparación'!L11 -> 9.28
A12: Jardín | B12: 3/4" | C12: 20000 | D12: =C12*'Comparación'!S12 -> 6900 | E12: =C12*'Comparación'!T12 -> 10432 | F12: =E12-D12 -> 3532 | G12: =C12*'Comparación'!E12/'Comparación'!C12 -> 10 | H12: =C12*'Comparación'!N12/'Comparación'!L12 -> 27.2
A13: Jardín | B13: 1" | C13: 3000 | D13: =C13*'Comparación'!S13 -> 1620 | E13: =C13*'Comparación'!T13 -> 2445 | F13: =E13-D13 -> 825 | G13: =C13*'Comparación'!E13/'Comparación'!C13 -> 4.32 | H13: =C13*'Comparación'!N13/'Comparación'!L13 -> 5.76
A14: TOTAL | C14: =SUM(C5:C13) -> 35025 | D14: =SUM(D5:D13) -> 21016 | E14: =SUM(E5:E13) -> 26238.608 | F14: =E14-D14 -> 5222.6083 | G14: =SUM(G5:G13) -> 71.952 | H14: =SUM(H5:H13) -> 93.306667
A16: Un contenedor 40HQ tiene unos 76 m³ interiores (~68 m³ útiles). Con Xiandai el mismo pedido no cabe: ajustar el mix o pedir su plan de carga.

Sheet Pedir a Xiandai
A1: Lo que falta pedirle a Xiandai
A2: Pedido por Pedro el 14-sep y no entregado, más lo recomendado
A4: # | B4: Qué pedir | C4: Por qué | D4: Estado
A5: 1 | B5: Presión de trabajo y de rotura (bar/psi) por medida | C5: Comparar con Dongying (8/24 bar en succión) | D5: Pendiente
A6: 2 | B6: Vacío máximo y radio mínimo de curvatura (succión) | C6: Uso en bombas y riego | D6: Pendiente
A7: 3 | B7: Rango de temperatura y protección UV | C7: Clave para la vida útil al sol (el problema actual) | D7: Pendiente
A8: 4 | B8: Ficha técnica / data sheet de cada manguera | C8: Respaldo por escrito | D8: Pendiente
A9: 5 | B9: Material: PVC virgen, % de carga, tipo de plastificante (DOTP/DOP), aditivo UV | C9: Es lo que define la durabilidad | D9: Pendiente
A10: 6 | B10: Muestras: succión 1" y jardín 3/4" | C10: Probar en terreno antes de comprar | D10: Pendiente
A11: 7 | B11: Informe de ensayo del producto cotizado (no de otra manguera) y respaldo de REACH | C11: El SGS enviado es de otro producto | D11: Pendiente
A12: 8 | B12: Plan de carga 40HQ y precio con embalaje (cajas/pallet) | C12: El precio es solo manguera; hoy el pedido no cabe | D12: Pendiente
A13: 9 | B13: Certificado de Origen Form F | C13: Arancel 0% con TLC Chile-China (sin él, 6%) | D13: Pendiente
A14: 10 | B14: Condiciones de pago y plazo de entrega; Trade Assurance de Alibaba | C14: Protección del pago | D14: Pendiente
A15: 11 | B15: Mejor precio en jardín (1/2", 3/4", 1") | C15: Está 51–95% sobre 2021 | D15: Pendiente

Sheet Costos importación
A1: Qué sumar al precio FOB
A2: Referencias generales; confirmar con el agente de aduana
A4: Concepto | B4: Referencia | C4: Fuente
A5: Precio FOB China | B5: Cotización del proveedor | C5: Cotizaciones
A6: Flete marítimo y seguro | B6: Pedir cotización al forwarder (40HQ Qingdao → San Antonio/Valparaíso) | C6: Pendiente
A7: Arancel aduanero | B7: 0% con TLC Chile-China y Certificado de Origen Form F; 6% sin certificado | C7: aduana.cl · hencargochile.com
A8: IVA importación | B8: 19% sobre CIF + arancel | C8: Norma general Chile
A9: Agente de aduana y gastos de puerto | B9: Según cotización del agente | C9: Pendiente
A10: Transporte a Curicó | B10: Según cotización | C10: Pendiente
A12: Fuentes:
A13: https://www.aduana.cl/tratado-de-libre-comercio-chile-china/aduana/2007-02-28/100917.html
A14: https://hencargochile.com/tratados-de-libre-comercio-en-chile-como-usar-el-certificado-de-origen-en-tu-despacho-aduanero-para-pagar-0-de-arancel/
A15: https://wfpvc.en.alibaba.com/
A16: https://wfpvc.goldsupplier.com/about.html
